examples/__init__.py
examples/example.py
itebooks/__init__.py
itebooks/itebooks.py
itebooks-0.3.1.dist-info/DESCRIPTION.rst
itebooks-0.3.1.dist-info/METADATA
itebooks-0.3.1.dist-info/RECORD
itebooks-0.3.1.dist-info/WHEEL
itebooks-0.3.1.dist-info/metadata.json
itebooks-0.3.1.dist-info/top_level.txt
