Metadata-Version: 2.0
Name: itebooks
Version: 0.3.1
Summary: Python wrapper for it-ebooks-api.
Home-page: https://github.com/aksbuzz/pyebooks
Author: Akshay
Author-email: akshayjr69@gmail.com
License: Copyright (c) 2017, Akshay.
